README.md
setup.py
imgproc/__init__.py
imgproc/draw.py
imgproc/image.py
imgproc.egg-info/PKG-INFO
imgproc.egg-info/SOURCES.txt
imgproc.egg-info/dependency_links.txt
imgproc.egg-info/requires.txt
imgproc.egg-info/top_level.txt